{
  "flags": [
    "low_confidence",
    "low_consensus"
  ],
  "plate_candidates": [
    {
      "text": "4ก51487",
      "score": 1.0660981915604493,
      "avg_conf": 0.35536606385348307,
      "count": 3,
      "consensus_ratio": 0.5
    },
    {
      "text": "4ก5148",
      "score": 0.5841736143039772,
      "avg_conf": 0.5841736143039772,
      "count": 1,
      "consensus_ratio": 0.16666666666666666
    },
    {
      "text": "4กฮ1487",
      "score": 0.5467884581914936,
      "avg_conf": 0.5467884581914936,
      "count": 1,
      "consensus_ratio": 0.16666666666666666
    }
  ],
  "province_candidates": [
    {
      "name": "กระบี่",
      "score": 90.0
    },
    {
      "name": "กาญจนบุรี",
      "score": 90.0
    },
    {
      "name": "จันทบุรี",
      "score": 90.0
    }
  ]
}